README.md
setup.py
module_resources/__init__.py
module_resources/json_module_resource.py
module_resources/module_resources.py
module_resources/yaml_module_resource.py
module_resources.egg-info/PKG-INFO
module_resources.egg-info/SOURCES.txt
module_resources.egg-info/dependency_links.txt
module_resources.egg-info/requires.txt
module_resources.egg-info/top_level.txt