Metadata-Version: 2.1
Name: module-resources
Version: 0.1.11
Summary: Import non-python files in a project directory as python namedtuple objects.
Home-page: https://github.com/captain-kark/module_resources
Author: Andrew Yurisich
Author-email: andrew.yurisich@gmail.com
License: MIT
Platform: UNKNOWN
Classifier: License :: OSI Approved :: MIT License
Classifier: Programming Language :: Python :: 3
Classifier: Programming Language :: Python :: 3.7
Provides-Extra: yaml
